mcp_open_client/__init__.py
mcp_open_client/cli.py
mcp_open_client/client.py
mcp_open_client/exceptions.py
mcp_open_client/api/__init__.py
mcp_open_client/api/main.py
mcp_open_client/api/endpoints/__init__.py
mcp_open_client/api/endpoints/chat.py
mcp_open_client/api/endpoints/providers.py
mcp_open_client/api/endpoints/registry.py
mcp_open_client/api/endpoints/servers.py
mcp_open_client/api/endpoints/sse.py
mcp_open_client/api/endpoints/conversations/__init__.py
mcp_open_client/api/endpoints/conversations/chat_endpoints.py
mcp_open_client/api/endpoints/conversations/context_endpoints.py
mcp_open_client/api/endpoints/conversations/conversations_endpoints.py
mcp_open_client/api/endpoints/conversations/dependencies.py
mcp_open_client/api/endpoints/conversations/editors_endpoints.py
mcp_open_client/api/endpoints/conversations/messages_endpoints.py
mcp_open_client/api/endpoints/conversations/tools_endpoints.py
mcp_open_client/api/models/__init__.py
mcp_open_client/api/models/chat.py
mcp_open_client/api/models/conversation.py
mcp_open_client/api/models/provider.py
mcp_open_client/api/models/registry.py
mcp_open_client/api/models/server.py
mcp_open_client/config/__init__.py
mcp_open_client/config/setup.py
mcp_open_client/config/defaults/ai_providers.json
mcp_open_client/config/defaults/mcp_servers.json
mcp_open_client/core/__init__.py
mcp_open_client/core/chat_service.py
mcp_open_client/core/lifecycle_manager.py
mcp_open_client/core/manager.py
mcp_open_client/core/process.py
mcp_open_client/core/provider_validator.py
mcp_open_client/core/registry_client.py
mcp_open_client/core/tool_operations.py
mcp_open_client/core/tool_service.py
mcp_open_client/core/transport_factory.py
mcp_open_client/core/conversations/__init__.py
mcp_open_client/core/conversations/chat_ops.py
mcp_open_client/core/conversations/context_ops.py
mcp_open_client/core/conversations/conversation_manager.py
mcp_open_client/core/conversations/conversation_ops.py
mcp_open_client-0.9.3.dist-info/licenses/LICENSE
mcp_open_client-0.9.3.dist-info/METADATA
mcp_open_client-0.9.3.dist-info/WHEEL
mcp_open_client-0.9.3.dist-info/entry_points.txt
mcp_open_client-0.9.3.dist-info/top_level.txt
mcp_open_client-0.9.3.dist-info/RECORD
